[
  {
    "model": "catalog.category",
    "pk": 11,
    "fields": {
      "name": "Смартфоны и гаджеты",
      "description": "Всегда в наличии последние модели"
    }
  },
  {
    "model": "catalog.category",
    "pk": 12,
    "fields": {
      "name": "Электроника",
      "description": "На каждый товар гарантия 2 года"
    }
  },
  {
    "model": "catalog.category",
    "pk": 13,
    "fields": {
      "name": "Мебель",
      "description": "Самая выгодная мебель от производителя"
    }
  },
  {
    "model": "catalog.category",
    "pk": 14,
    "fields": {
      "name": "Техника для кухни",
      "description": "Самый большой выбор"
    }
  }
]